assumeless/__init__.py
assumeless/cli.py
assumeless/analysis/__init__.py
assumeless/analysis/ast_visitor.py
assumeless/analysis/suppression.py
assumeless/cli/__init__.py
assumeless/cli/main.py
assumeless/cli/render.py
assumeless/core/__init__.py
assumeless/core/cache.py
assumeless/core/config.py
assumeless/core/doc_checker.py
assumeless/core/doctor.py
assumeless/core/engine.py
assumeless/core/models.py
assumeless/rules/__init__.py
assumeless/rules/ast_rule.py
assumeless/rules/base.py
assumeless/rules/deployment.py
assumeless/rules/silent.py
assumeless/rules/cohesion/__init__.py
assumeless/rules/portability/__init__.py
assumeless/rules/portability/hardcoded_paths.py
assumeless/rules/reliability/__init__.py
assumeless/rules/reliability/broad_except.py
assumeless/rules/reliability/mutable_defaults.py
assumeless/rules/reliability/silent_except.py
assumeless/rules/reliability/todo_marker.py
assumeless/rules/reliability/unclosed_files.py
assumeless/rules/security/__init__.py
assumeless/rules/security/env_vars.py
assumeless/utils/__init__.py
assumeless/utils/formatting.py
assumeless-1.0.0.dist-info/METADATA
assumeless-1.0.0.dist-info/WHEEL
assumeless-1.0.0.dist-info/entry_points.txt
assumeless-1.0.0.dist-info/licenses/LICENSE
assumeless-1.0.0.dist-info/RECORD
