Metadata-Version: 2.4
Name: assumeless
Version: 1.0.0
Summary: An assumptions-first diagnostic tool that aims to surface dangerous hidden assumptions in code.
Project-URL: Homepage, https://github.com/huntwter/assumeless
Project-URL: Documentation, https://github.com/huntwter/assumeless/docs
Project-URL: Repository, https://github.com/huntwter/assumeless
Author-email: Jatin Sharma <huntwter.dev@gmail.com>
License-Expression: Apache-2.0
License-File: LICENSE
Keywords: assumptions,cli,code-quality,security,static-analysis
Classifier: Development Status :: 5 - Production/Stable
Classifier: Intended Audience :: Developers
Classifier: License :: OSI Approved :: Apache Software License
Classifier: Programming Language :: Python :: 3.9
Classifier: Programming Language :: Python :: 3.10
Classifier: Programming Language :: Python :: 3.11
Classifier: Topic :: Software Development :: Quality Assurance
Requires-Python: >=3.9
Requires-Dist: click>=8.1.0
Requires-Dist: rich>=13.0.0
Requires-Dist: toml>=0.10.2
